notebookc2/__init__.py
notebookc2/notebookc2.py
notebookc2-0.0.9.dist-info/LICENSE
notebookc2-0.0.9.dist-info/METADATA
notebookc2-0.0.9.dist-info/WHEEL
notebookc2-0.0.9.dist-info/top_level.txt
notebookc2-0.0.9.dist-info/RECORD
